{
  "usedBassGuitar": [
    {
      "name": "Бас-гитара Warwick Rockbass Streamer 4 H-H Black China 2010's",
      "price": "35 990 ₽",
      "type": "used",
      "characteristics": {
        "codeOfItem": "481278",
        "type": "Бас-гитара",
        "nameOfBrand": "Warwick",
        "series": "Black Label",
        "condition": "Очень хорошее",
        "country": "Китай",
        "bodyShape": "Streamer",
        "orientation": "под правую руку",
        "valueOfStrings": "4",
        "valueOfFrets": "24",
        "widthOfUpperSill": "34",
        "deck": "сосна",
        "neck": "клен",
        "fingerboard": "палисандр",
        "colorOfBody": "черный",
        "electronics": "пассивная",
        "pickupsSchema": "H-H",
        "fixingNeck": "на болтах",
        "article": "Вес: 5 кг"
      }
    },
    {
      "name": "Бас-гитара Burny MB-90 P Black Japan 1990s",
      "price": "76 990 ₽",
      "type": "used",
      "characteristics": {
        "codeOfItem": "554417",
        "type": "Бас-гитара",
        "nameOfBrand": "Burny",
        "condition": "Очень хорошее",
        "country": "Япония",
        "bodyShape": "Mockingbird",
        "orientation": "под правую руку",
        "valueOfStrings": "4",
        "valueOfFrets": "24",
        "widthOfUpperSill": "34",
        "widthOfUpperThreshold": "42",
        "deck": "махагони",
        "neck": "клен",
        "fingerboard": "палисандр",
        "colorOfBody": "черный",
        "electronics": "пассивная",
        "pickupsSchema": "P",
        "fixingNeck": "сквозное",
        "article": "Вес: 5 кг"
      }
    },
    {
      "name": "Fender Jazz Bass Marcus Miller JB77-195MM",
      "price": "199 990 ₽",
      "type": "used",
      "characteristics": {
        "codeOfItem": "556654",
        "type": "Бас-гитара",
        "condition": "Очень хорошее",
        "country": "Япония",
        "bodyShape": "Jazz Bass",
        "orientation": "под правую руку",
        "valueOfStrings": "4",
        "valueOfFrets": "20",
        "widthOfUpperSill": "34",
        "widthOfUpperThreshold": "38",
        "deck": "ясень",
        "neck": "клен",
        "fingerboard": "клен",
        "colorOfBody": "натуральный",
        "electronics": "активная",
        "pickupsSchema": "S-S",
        "fixingNeck": "на болтах",
        "article": "Вес: 5 кг"
      }
    },
    {
      "name": "Бас-гитара Washburn XB925 Natural H-H USA 2000'S W/Case",
      "price": "184 990 ₽",
      "type": "used",
      "characteristics": {
        "codeOfItem": "554242",
        "type": "Бас-гитара",
        "nameOfBrand": "Washburn",
        "condition": "Превосходное",
        "country": "США",
        "bodyShape": "Superstrat",
        "orientation": "под правую руку",
        "valueOfStrings": "5",
        "valueOfFrets": "24",
        "widthOfUpperSill": "34",
        "deck": "ясень",
        "neck": "клен",
        "fingerboard": "палисандр",
        "colorOfBody": "натуральный",
        "included": "кейс",
        "electronics": "активная",
        "pickupsSchema": "H-H",
        "fixingNeck": "на болтах",
        "article": "Вес: 5 кг"
      }
    },
    {
      "name": "Бас-гитара Rickenbacker 4001 USA 1979 w/case H-H",
      "price": "399 990 ₽",
      "type": "used",
      "characteristics": {
        "codeOfItem": "553214",
        "type": "Бас-гитара",
        "nameOfBrand": "Rickenbacker",
        "condition": "Среднее",
        "bodyShape": "Double cut",
        "orientation": "под правую руку",
        "valueOfStrings": "4",
        "valueOfFrets": "20",
        "widthOfUpperSill": "33.25",
        "deck": "клен",
        "neck": "клен",
        "fingerboard": "падук",
        "colorOfBody": "черный",
        "included": "чехол",
        "electronics": "пассивная",
        "pickupsSchema": "H-H",
        "fixingNeck": "сквозное",
        "article": "Вес: 5 кг"
      }
    },
    {
      "name": "Бас-гитара Burns Bison Bass White S-S-S Korea 1990's",
      "price": "100 000 ₽",
      "type": "used",
      "characteristics": {
        "codeOfItem": "532080",
        "type": "Бас-гитара",
        "condition": "Превосходное",
        "country": "Корея",
        "bodyShape": "Double cut",
        "orientation": "под правую руку",
        "valueOfStrings": "6",
        "valueOfFrets": "22",
        "widthOfUpperSill": "34",
        "deck": "нато",
        "neck": "клен",
        "fingerboard": "орех",
        "colorOfBody": "белый",
        "included": "чехол",
        "electronics": "активная",
        "pickupsSchema": "S-S-S",
        "fixingNeck": "на болтах",
        "article": "Вес: 5 кг"
      }
    },
    {
      "name": "Бас-гитара Ibanez SR360 Purple Japan 1994",
      "price": "46 990 ₽",
      "type": "used",
      "characteristics": {
        "codeOfItem": "556656",
        "type": "Бас-гитара",
        "condition": "Хорошее",
        "bodyShape": "Double cut",
        "orientation": "под правую руку",
        "valueOfStrings": "4",
        "valueOfFrets": "24",
        "widthOfUpperSill": "32",
        "deck": "липа",
        "neck": "клен",
        "fingerboard": "палисандр",
        "colorOfBody": "фиолетовый",
        "electronics": "пассивная",
        "pickupsSchema": "P-J",
        "fixingNeck": "на болтах",
        "article": "Вес: 5 кг"
      }
    },
    {
      "name": "Бас гитара Fender Squier Affinity Red China 2000s",
      "price": "33 990 ₽",
      "type": "used",
      "characteristics": {
        "codeOfItem": "554951",
        "type": "Бас-гитара",
        "nameOfBrand": "Squier by Fender",
        "condition": "Хорошее",
        "bodyShape": "Precision Bass",
        "orientation": "под правую руку",
        "valueOfStrings": "4",
        "valueOfFrets": "20",
        "widthOfUpperSill": "34",
        "deck": "тополь",
        "neck": "клен",
        "fingerboard": "лавр",
        "colorOfBody": "красный",
        "electronics": "пассивная",
        "pickupsSchema": "P",
        "fixingNeck": "на болтах",
        "article": "Вес: 5 кг"
      }
    },
    {
      "name": "Бас-гитара Fernandes FRB 60 PJ Black Japan 1990's",
      "price": "61 990 ₽",
      "type": "used",
      "characteristics": {
        "codeOfItem": "554993",
        "type": "Бас-гитара",
        "nameOfBrand": "Fernandes",
        "condition": "Очень хорошее",
        "country": "Япония",
        "bodyShape": "Double cut",
        "orientation": "под правую руку",
        "valueOfStrings": "4",
        "valueOfFrets": "24",
        "widthOfUpperSill": "34",
        "deck": "липа",
        "neck": "клен",
        "fingerboard": "палисандр",
        "colorOfBody": "черный",
        "electronics": "активная",
        "pickupsSchema": "P-J",
        "fixingNeck": "на болтах",
        "article": "Вес: 5 кг"
      }
    },
    {
      "name": "Бас-гитара Fernandes RPB360 Precision Bass Snow White (Уценка)",
      "price": "24 990 ₽",
      "type": "used",
      "characteristics": {
        "codeOfItem": "544060",
        "type": "Бас-гитара",
        "nameOfBrand": "Fernandes",
        "condition": "Хорошее",
        "country": "Тайвань",
        "bodyShape": "Precision Bass",
        "orientation": "под правую руку",
        "valueOfStrings": "4",
        "valueOfFrets": "20",
        "widthOfUpperSill": "34",
        "deck": "ольха",
        "neck": "клен",
        "fingerboard": "палисандр",
        "colorOfBody": "белый",
        "electronics": "пассивная",
        "pickupsSchema": "P",
        "fixingNeck": "на болтах",
        "article": "Вес: 5 кг"
      }
    },
    {
      "name": "Бас-гитара Schecter Damien Elite-4 HH Transparent Black Indonesia 2014",
      "price": "59 990 ₽",
      "type": "used",
      "characteristics": {
        "codeOfItem": "514220",
        "type": "Бас-гитара",
        "nameOfBrand": "Schecter",
        "series": "Damien Elite",
        "condition": "Хорошее",
        "country": "Индонезия",
        "bodyShape": "Double cut",
        "orientation": "под правую руку",
        "valueOfStrings": "4",
        "valueOfFrets": "24",
        "widthOfUpperSill": "34",
        "deck": "махагони",
        "neck": "клен",
        "fingerboard": "палисандр",
        "colorOfBody": "черный",
        "included": "ремень",
        "electronics": "активная",
        "pickupsSchema": "H-H",
        "fixingNeck": "на болтах",
        "article": "Вес: 5 кг"
      }
    },
    {
      "name": "Бас-гитара Edwards HEJ-95 See Thru Blue JS-80B x 3 Japan 1995",
      "price": "61 990 ₽",
      "type": "used",
      "characteristics": {
        "codeOfItem": "474460",
        "type": "Бас-гитара",
        "nameOfBrand": "Edwards",
        "condition": "Хорошее",
        "bodyShape": "Jazz Bass",
        "orientation": "под правую руку",
        "valueOfStrings": "4",
        "valueOfFrets": "22",
        "widthOfUpperSill": "34",
        "deck": "ясень",
        "neck": "клен",
        "fingerboard": "клен",
        "colorOfBody": "голубой",
        "electronics": "пассивная",
        "pickupsSchema": "S-S-S",
        "fixingNeck": "на болтах",
        "article": "Вес: 5 кг"
      }
    },
    {
      "name": "Бас-гитара Bosstone BGP-5 3TS+Bag  5 струнная (Уценка)",
      "price": "16 250 ₽",
      "type": "used",
      "characteristics": {
        "codeOfItem": "551305",
        "type": "Бас-гитара",
        "nameOfBrand": "не указан",
        "condition": "Плохое",
        "bodyShape": "Double cut",
        "orientation": "под правую руку",
        "valueOfStrings": "5",
        "valueOfFrets": "20",
        "widthOfUpperSill": "34",
        "deck": "платан",
        "neck": "клен",
        "fingerboard": "HDF",
        "colorOfBody": "санберст",
        "electronics": "пассивная",
        "pickupsSchema": "S-S",
        "fixingNeck": "на болтах",
        "article": "Вес: 5 кг"
      }
    },
    {
      "name": "Бас-гитара Greco GOB-900 Speedway  HH  1979 Japan W/Gigbag",
      "price": "69 990 ₽",
      "type": "used",
      "characteristics": {
        "codeOfItem": "546353",
        "type": "Бас-гитара",
        "nameOfBrand": "Greco",
        "condition": "Хорошее",
        "bodyShape": "StingRay",
        "orientation": "под правую руку",
        "valueOfStrings": "4",
        "valueOfFrets": "22",
        "widthOfUpperSill": "34",
        "deck": "клен, ясень, махагони",
        "neck": "клен",
        "fingerboard": "палисандр",
        "colorOfBody": "натуральный",
        "electronics": "пассивная",
        "pickupsSchema": "H-H",
        "fixingNeck": "сквозное",
        "article": "D794799",
        "weight": "5 кг"
      }
    },
    {
      "name": "Бас-гитара Sire Marcus Miller V7 Jazz Bass SS Sunburst Indonesia 2010's",
      "price": "76 000 ₽",
      "type": "used",
      "characteristics": {
        "codeOfItem": "495824",
        "type": "Бас-гитара",
        "nameOfBrand": "Sire",
        "condition": "Очень хорошее",
        "country": "Индонезия",
        "bodyShape": "Jazz Bass",
        "orientation": "под правую руку",
        "valueOfStrings": "4",
        "valueOfFrets": "20",
        "widthOfUpperSill": "34",
        "widthOfUpperThreshold": "38",
        "deck": "ясень",
        "neck": "клен",
        "fingerboard": "клен",
        "colorOfBody": "санберст",
        "electronics": "активная",
        "pickupsSchema": "S-S",
        "fixingNeck": "на болтах",
        "article": "15370440",
        "weight": "5 кг"
      }
    },
    {
      "name": "Бас-гитара Roscoe SKB 3005 HH Naural USA 2011 w\\Case",
      "price": "415 990 ₽",
      "type": "used",
      "characteristics": {
        "codeOfItem": "540392",
        "type": "Бас-гитара",
        "condition": "Превосходное",
        "country": "США",
        "bodyShape": "Double cut",
        "orientation": "под правую руку",
        "valueOfStrings": "5",
        "valueOfFrets": "24",
        "widthOfUpperSill": "34",
        "deck": "клен, ясень",
        "neck": "клен",
        "fingerboard": "вишня",
        "colorOfBody": "желтый",
        "electronics": "активная",
        "pickupsSchema": "H-H",
        "fixingNeck": "на болтах",
        "article": "Вес: 5 кг"
      }
    },
    {
      "name": "Бас-гитара Fender Precision Elite II Natural USA 1983s w/case",
      "price": "384 990 ₽",
      "type": "used",
      "characteristics": {
        "codeOfItem": "523137",
        "type": "Бас-гитара",
        "nameOfBrand": "Fender",
        "series": "Elite Series",
        "condition": "Превосходное",
        "country": "США",
        "bodyShape": "Precision Bass",
        "orientation": "под правую руку",
        "valueOfStrings": "4",
        "valueOfFrets": "20",
        "widthOfUpperSill": "34",
        "deck": "ясень",
        "neck": "клен",
        "fingerboard": "клен",
        "colorOfBody": "натуральный",
        "included": "кейс",
        "electronics": "активная",
        "pickupsSchema": "H-H",
        "fixingNeck": "на болтах",
        "article": "E318993",
        "weight": "5 кг"
      }
    },
    {
      "name": "Бас-гитара Gold Tone BB-400 H Brown Case USA 2022",
      "price": "169 990 ₽",
      "type": "used",
      "characteristics": {
        "codeOfItem": "545143",
        "type": "Бас-гитара",
        "nameOfBrand": "Gold Tone",
        "condition": "Очень хорошее",
        "country": "США",
        "bodyShape": "классическая",
        "orientation": "под правую руку",
        "valueOfStrings": "4",
        "valueOfFrets": "20",
        "widthOfUpperSill": "32",
        "widthOfUpperThreshold": "47.6",
        "deck": "клен",
        "neck": "клен",
        "fingerboard": "палисандр",
        "colorOfBody": "коричневый",
        "included": "кейс",
        "electronics": "пассивная",
        "pickupsSchema": "H",
        "fixingNeck": "на клею",
        "article": "Вес: 5 кг"
      }
    },
    {
      "name": "Бас-гитара ESP LTD B 405 SM NS Korea 2010's",
      "price": "153 990 ₽",
      "type": "used",
      "characteristics": {
        "codeOfItem": "552463",
        "type": "Бас-гитара",
        "nameOfBrand": "LTD",
        "condition": "Очень хорошее",
        "country": "Корея",
        "bodyShape": "Double cut",
        "orientation": "под правую руку",
        "valueOfStrings": "5",
        "valueOfFrets": "24",
        "widthOfUpperSill": "34",
        "deck": "клен, ясень",
        "neck": "клен, орех",
        "fingerboard": "палисандр",
        "colorOfBody": "натуральный",
        "electronics": "активная",
        "pickupsSchema": "H-H",
        "fixingNeck": "сквозное",
        "article": "Вес: 5 кг"
      }
    },
    {
      "name": "Бас-гитара Gibson LP НН Sunburst w/Case USA 2002",
      "price": "153 990 ₽",
      "type": "used",
      "characteristics": {
        "codeOfItem": "488336",
        "type": "Бас-гитара",
        "nameOfBrand": "Gibson",
        "condition": "Среднее",
        "country": "США",
        "bodyShape": "Les Paul",
        "orientation": "под правую руку",
        "valueOfStrings": "4",
        "valueOfFrets": "20",
        "widthOfUpperSill": "34",
        "widthOfUpperThreshold": "41",
        "deck": "клен, махагони",
        "neck": "махагони",
        "fingerboard": "черное дерево",
        "colorOfBody": "санберст",
        "included": "кейс",
        "electronics": "пассивная",
        "pickupsSchema": "H-H",
        "fixingNeck": "на клею",
        "article": "027450698",
        "weight": "5 кг"
      }
    },
    {
      "name": "Бас-гитара Yamaha TRBX505 TBN Indonesia 2000s",
      "price": "111 000 ₽",
      "type": "used",
      "characteristics": {
        "codeOfItem": "544085",
        "type": "Бас-гитара",
        "nameOfBrand": "Yamaha",
        "condition": "Очень хорошее",
        "country": "Индонезия",
        "bodyShape": "Double cut",
        "orientation": "под правую руку",
        "valueOfStrings": "5",
        "valueOfFrets": "24",
        "widthOfUpperSill": "34",
        "widthOfUpperThreshold": "43",
        "deck": "махагони",
        "neck": "клен",
        "fingerboard": "палисандр",
        "colorOfBody": "коричневый",
        "electronics": "активная",
        "pickupsSchema": "H-H",
        "fixingNeck": "на болтах",
        "article": "Вес: 5 кг"
      }
    },
    {
      "name": "Бас-гитара Fender Precision Bass Pre-CBS Gold Guard Sunburst USA 1958 w/ Tweed Case",
      "price": "3 306 990 ₽",
      "type": "used",
      "characteristics": {
        "codeOfItem": "555918",
        "type": "Бас-гитара",
        "nameOfBrand": "Fender",
        "series": "American Original '50s Precision Bass",
        "condition": "Превосходное",
        "country": "США",
        "bodyShape": "Precision Bass",
        "orientation": "под правую руку",
        "valueOfStrings": "4",
        "valueOfFrets": "20",
        "widthOfUpperSill": "34",
        "deck": "ольха",
        "neck": "клен",
        "fingerboard": "клен",
        "colorOfBody": "санберст",
        "included": "кейс",
        "electronics": "пассивная",
        "pickupsSchema": "P",
        "fixingNeck": "на болтах",
        "article": "Вес: 5 кг"
      }
    },
    {
      "name": "Бас-гитара Fender Jazz Bass JJ Olympic White w/case USA 1964",
      "price": "4 068 990 ₽",
      "type": "used",
      "characteristics": {
        "codeOfItem": "553550",
        "type": "Бас-гитара",
        "nameOfBrand": "Fender",
        "condition": "Очень хорошее",
        "country": "США",
        "bodyShape": "Jazz Bass",
        "orientation": "под правую руку",
        "valueOfStrings": "4",
        "valueOfFrets": "20",
        "widthOfUpperSill": "34",
        "widthOfUpperThreshold": "38.1",
        "deck": "ольха",
        "neck": "клен",
        "fingerboard": "палисандр",
        "colorOfBody": "белый",
        "included": "кейс",
        "electronics": "пассивная",
        "pickupsSchema": "J-J",
        "fixingNeck": "на болтах",
        "article": "Вес: 5 кг"
      }
    },
    {
      "name": "Бас-гитара Fender Precision Bass Pre-CBS Sherwood Green (Riggio) USA 1964 w/Case",
      "price": "2 122 990 ₽",
      "type": "used",
      "characteristics": {
        "codeOfItem": "555917",
        "type": "Бас-гитара",
        "nameOfBrand": "Fender",
        "series": "American Original '60s Precision Bass",
        "condition": "Очень хорошее",
        "country": "США",
        "bodyShape": "Precision Bass",
        "orientation": "под правую руку",
        "valueOfStrings": "4",
        "valueOfFrets": "20",
        "widthOfUpperSill": "34",
        "deck": "ольха",
        "neck": "клен",
        "fingerboard": "палисандр",
        "colorOfBody": "зеленый",
        "included": "кейс",
        "electronics": "пассивная",
        "pickupsSchema": "P",
        "fixingNeck": "на болтах",
        "article": "Вес: 5 кг"
      }
    },
    {
      "name": "Бас-гитара Fender Jazz Bass Pre-CBS Sunburst USA 1963 w/Case",
      "price": "3 401 990 ₽",
      "type": "used",
      "characteristics": {
        "codeOfItem": "553142",
        "type": "Бас-гитара",
        "nameOfBrand": "Fender",
        "series": "American Original '60s Jazz Bass",
        "condition": "Очень хорошее",
        "country": "США",
        "bodyShape": "Jazz Bass",
        "orientation": "под правую руку",
        "valueOfStrings": "4",
        "valueOfFrets": "20",
        "widthOfUpperSill": "34",
        "deck": "ольха",
        "neck": "клен",
        "fingerboard": "палисандр",
        "colorOfBody": "санберст",
        "included": "кейс",
        "electronics": "пассивная",
        "pickupsSchema": "J-J",
        "fixingNeck": "на болтах",
        "article": "Вес: 5 кг"
      }
    },
    {
      "name": "Бас-гитара Rickenbacker 4001 Vintage Bass Mapleglo USA 1973 w/ Checkerboard Binding, Toaster, Case",
      "price": "1 187 990 ₽",
      "type": "used",
      "characteristics": {
        "codeOfItem": "556335",
        "type": "Бас-гитара",
        "nameOfBrand": "Rickenbacker",
        "series": "4000 Series",
        "condition": "Очень хорошее",
        "country": "США",
        "bodyShape": "Double cut",
        "orientation": "под правую руку",
        "valueOfStrings": "4",
        "valueOfFrets": "22",
        "widthOfUpperSill": "34",
        "deck": "клен",
        "neck": "клен",
        "fingerboard": "палисандр",
        "colorOfBody": "натуральный",
        "included": "кейс",
        "electronics": "пассивная",
        "pickupsSchema": "H-H",
        "fixingNeck": "сквозное",
        "article": "Вес: 5 кг"
      }
    },
    {
      "name": "Бас-гитара Fender Mustang Bass Short Scale Dakota Red USA 1967 w/ Case",
      "price": "1 074 990 ₽",
      "type": "used",
      "characteristics": {
        "codeOfItem": "555912",
        "type": "Бас-гитара",
        "nameOfBrand": "Fender",
        "condition": "Очень хорошее",
        "country": "США",
        "bodyShape": "Mustang",
        "orientation": "под правую руку",
        "valueOfStrings": "6",
        "valueOfFrets": "21",
        "widthOfUpperSill": "30",
        "deck": "ольха",
        "neck": "клен",
        "fingerboard": "палисандр",
        "colorOfBody": "красный",
        "included": "кейс",
        "electronics": "пассивная",
        "pickupsSchema": "P",
        "fixingNeck": "на болтах",
        "article": "Вес: 5 кг"
      }
    },
    {
      "name": "Бас-гитара Gibson EB-0 SG Bass S Cherry w/case USA 1961",
      "price": "596 990 ₽",
      "type": "used",
      "characteristics": {
        "codeOfItem": "556034",
        "type": "Бас-гитара",
        "nameOfBrand": "Gibson",
        "condition": "Хорошее",
        "country": "США",
        "bodyShape": "SG",
        "orientation": "под правую руку",
        "valueOfStrings": "4",
        "valueOfFrets": "20",
        "widthOfUpperSill": "30.5",
        "widthOfUpperThreshold": "42.8",
        "deck": "махагони",
        "neck": "махагони",
        "fingerboard": "палисандр",
        "colorOfBody": "красный",
        "included": "кейс",
        "electronics": "пассивная",
        "pickupsSchema": "S",
        "fixingNeck": "на клею",
        "article": "Вес: 5 кг"
      }
    },
    {
      "name": "Бас-гитара Fender Order Made Jazz Bass Butterscotch Lacquer Japan 1993 w/ Case",
      "price": "481 990 ₽",
      "type": "used",
      "characteristics": {
        "codeOfItem": "554640",
        "type": "Бас-гитара",
        "nameOfBrand": "Fender",
        "series": "Order Made",
        "condition": "Превосходное",
        "country": "Япония",
        "bodyShape": "Jazz Bass",
        "orientation": "под правую руку",
        "valueOfStrings": "4",
        "valueOfFrets": "20",
        "widthOfUpperSill": "34",
        "deck": "ясень",
        "neck": "клен",
        "fingerboard": "палисандр",
        "colorOfBody": "натуральный",
        "included": "кейс",
        "electronics": "пассивная",
        "pickupsSchema": "J-J",
        "fixingNeck": "на болтах",
        "article": "Вес: 5 кг"
      }
    },
    {
      "name": "Бас-гитара Fender JV Jazz Bass ‘62 Vintage Reissue JB62-75 Candy Apple Red Japan 1983",
      "price": "425 990 ₽",
      "type": "used",
      "characteristics": {
        "codeOfItem": "555909",
        "type": "Бас-гитара",
        "nameOfBrand": "Fender",
        "series": "Vintage Reissue",
        "condition": "Превосходное",
        "country": "Япония",
        "bodyShape": "Jazz Bass",
        "orientation": "под правую руку",
        "valueOfStrings": "4",
        "valueOfFrets": "20",
        "widthOfUpperSill": "34",
        "deck": "ольха",
        "neck": "клен",
        "fingerboard": "палисандр",
        "colorOfBody": "красный",
        "included": "чехол",
        "electronics": "пассивная",
        "pickupsSchema": "J-J",
        "fixingNeck": "на болтах",
        "article": "Вес: 5 кг"
      }
    },
    {
      "name": "Бас-гитара Fender Marcus Miller Jazz Bass Natural Ash Japan 2004 w/ Active EQ",
      "price": "384 990 ₽",
      "type": "used",
      "characteristics": {
        "codeOfItem": "554650",
        "type": "Бас-гитара",
        "nameOfBrand": "Fender",
        "series": "Signature",
        "condition": "Превосходное",
        "country": "Япония",
        "bodyShape": "Jazz Bass",
        "orientation": "под правую руку",
        "valueOfStrings": "4",
        "valueOfFrets": "20",
        "widthOfUpperSill": "34",
        "deck": "ясень",
        "neck": "клен",
        "fingerboard": "клен",
        "colorOfBody": "натуральный",
        "included": "чехол",
        "electronics": "активная",
        "pickupsSchema": "J-J",
        "fixingNeck": "на болтах",
        "article": "Вес: 5 кг"
      }
    },
    {
      "name": "Бас-гитара Fender Order Made Jazz Bass JB62 Trans Red Ash Japan 1987",
      "price": "364 990 ₽",
      "type": "used",
      "characteristics": {
        "codeOfItem": "553558",
        "type": "Бас-гитара",
        "nameOfBrand": "Fender",
        "series": "Order Made",
        "condition": "Превосходное",
        "country": "Япония",
        "bodyShape": "Jazz Bass",
        "orientation": "под правую руку",
        "valueOfStrings": "4",
        "valueOfFrets": "22",
        "widthOfUpperSill": "34",
        "deck": "ясень",
        "neck": "клен",
        "fingerboard": "палисандр",
        "colorOfBody": "красный",
        "included": "чехол",
        "electronics": "пассивная",
        "pickupsSchema": "J-J",
        "fixingNeck": "на болтах",
        "article": "Вес: 5 кг"
      }
    },
    {
      "name": "Бас-гитара Fender Jazz Bass ‘75 Vintage Reissue JB75-80 Natural Japan 1987",
      "price": "307 990 ₽",
      "type": "used",
      "characteristics": {
        "codeOfItem": "555911",
        "type": "Бас-гитара",
        "nameOfBrand": "Fender",
        "series": "Vintage Reissue",
        "condition": "Превосходное",
        "country": "Япония",
        "bodyShape": "Jazz Bass",
        "orientation": "под правую руку",
        "valueOfStrings": "4",
        "valueOfFrets": "20",
        "widthOfUpperSill": "34",
        "deck": "ясень",
        "neck": "клен",
        "fingerboard": "клен",
        "colorOfBody": "натуральный",
        "electronics": "пассивная",
        "pickupsSchema": "J-J",
        "fixingNeck": "на болтах",
        "article": "Вес: 5 кг"
      }
    },
    {
      "name": "Бас-гитара Fender Jazz Bass ‘62 Vintage Reissue JB62-58 Sunburst Japan 1993 w/Case",
      "price": "269 990 ₽",
      "type": "used",
      "characteristics": {
        "codeOfItem": "555915",
        "type": "Бас-гитара",
        "nameOfBrand": "Fender",
        "series": "Vintage Reissue",
        "condition": "Превосходное",
        "country": "Япония",
        "bodyShape": "Jazz Bass",
        "orientation": "под правую руку",
        "valueOfStrings": "4",
        "valueOfFrets": "20",
        "widthOfUpperSill": "34",
        "deck": "липа",
        "neck": "клен",
        "fingerboard": "палисандр",
        "colorOfBody": "санберст",
        "included": "кейс",
        "electronics": "пассивная",
        "pickupsSchema": "J-J",
        "fixingNeck": "на болтах",
        "article": "Вес: 5 кг"
      }
    },
    {
      "name": "Бас-гитара Fender Limited Edition International Color Jazz Bass Monaco Yellow Japan 2022",
      "price": "231 990 ₽",
      "type": "used",
      "characteristics": {
        "codeOfItem": "554647",
        "type": "Бас-гитара",
        "nameOfBrand": "Fender",
        "condition": "Превосходное",
        "country": "Япония",
        "bodyShape": "Jazz Bass",
        "orientation": "под правую руку",
        "valueOfStrings": "4",
        "valueOfFrets": "20",
        "widthOfUpperSill": "34",
        "deck": "липа",
        "neck": "клен",
        "fingerboard": "клен",
        "colorOfBody": "желтый",
        "included": "чехол",
        "electronics": "пассивная",
        "pickupsSchema": "J-J",
        "fixingNeck": "на болтах",
        "article": "Вес: 5 кг"
      }
    },
    {
      "name": "Бас-гитара Fender Jazz Bass Sunburst USA 1966 w/Case",
      "price": "1 741 990 ₽",
      "type": "used",
      "characteristics": {
        "codeOfItem": "552515",
        "type": "Бас-гитара",
        "nameOfBrand": "Fender",
        "series": "American Original '60s Jazz Bass",
        "condition": "Очень хорошее",
        "country": "США",
        "bodyShape": "Jazz Bass",
        "orientation": "под правую руку",
        "valueOfStrings": "4",
        "valueOfFrets": "20",
        "widthOfUpperSill": "34",
        "deck": "ольха",
        "neck": "клен",
        "fingerboard": "палисандр",
        "colorOfBody": "санберст",
        "included": "кейс",
        "electronics": "пассивная",
        "pickupsSchema": "J",
        "fixingNeck": "на болтах",
        "article": "Вес: 5 кг"
      }
    },
    {
      "name": "Бас-гитара Fender Jazz Bass JJ Sunburst w/case USA 1972",
      "price": "1 340 990 ₽",
      "type": "used",
      "characteristics": {
        "codeOfItem": "553551",
        "type": "Бас-гитара",
        "nameOfBrand": "Fender",
        "condition": "Превосходное",
        "country": "США",
        "bodyShape": "Jazz Bass",
        "orientation": "под правую руку",
        "valueOfStrings": "4",
        "valueOfFrets": "20",
        "widthOfUpperSill": "34",
        "widthOfUpperThreshold": "38.1",
        "deck": "ясень",
        "neck": "клен",
        "fingerboard": "палисандр",
        "colorOfBody": "санберст",
        "included": "кейс",
        "electronics": "пассивная",
        "pickupsSchema": "J-J",
        "fixingNeck": "на болтах",
        "article": "Вес: 5 кг"
      }
    },
    {
      "name": "Бас-гитара Steinberger XL-2 Vintage Headless Bass White USA 1988 w/ EMGs Kick-Stand Case",
      "price": "1 164 990 ₽",
      "type": "used",
      "characteristics": {
        "codeOfItem": "532810",
        "type": "Бас-гитара",
        "nameOfBrand": "Steinberger",
        "condition": "Превосходное",
        "country": "США",
        "bodyShape": "Offset, Headless",
        "orientation": "под правую руку",
        "valueOfStrings": "4",
        "valueOfFrets": "24",
        "widthOfUpperSill": "34",
        "deck": "стекловолокно",
        "neck": "стекловолокно",
        "fingerboard": "эпоксидная смола",
        "colorOfBody": "белый",
        "included": "кейс",
        "electronics": "активная",
        "pickupsSchema": "H-H",
        "fixingNeck": "сквозное",
        "article": "Вес: 5 кг"
      }
    },
    {
      "name": "Бас-гитара Fender Precision Bass J Ocean Turquoise w/case USA 1969",
      "price": "973 990 ₽",
      "type": "used",
      "characteristics": {
        "codeOfItem": "531969",
        "type": "Бас-гитара",
        "nameOfBrand": "Fender",
        "condition": "Превосходное",
        "country": "США",
        "bodyShape": "Precision Bass",
        "orientation": "под правую руку",
        "valueOfStrings": "4",
        "valueOfFrets": "20",
        "widthOfUpperSill": "34",
        "widthOfUpperThreshold": "41.2",
        "deck": "ольха",
        "neck": "клен",
        "fingerboard": "палисандр",
        "colorOfBody": "зеленый",
        "included": "кейс",
        "electronics": "пассивная",
        "pickupsSchema": "J",
        "fixingNeck": "на болтах",
        "article": "Вес: 5 кг"
      }
    },
    {
      "name": "Бас-гитара Hofner 500/1 Beatle Bass Vintage Violin Germany 1973 w/Blade Pickups",
      "price": "934 990 ₽",
      "type": "used",
      "characteristics": {
        "codeOfItem": "509563",
        "type": "Бас-гитара",
        "nameOfBrand": "Hofner",
        "condition": "Очень хорошее",
        "country": "Германия",
        "bodyShape": "Violin Bass",
        "orientation": "под правую руку",
        "valueOfStrings": "4",
        "valueOfFrets": "22",
        "widthOfUpperSill": "30",
        "widthOfUpperThreshold": "43",
        "deck": "клен",
        "neck": "клен",
        "fingerboard": "палисандр",
        "colorOfBody": "санберст",
        "electronics": "пассивная",
        "pickupsSchema": "S-S",
        "fixingNeck": "на клею",
        "article": "Вес: 5 кг"
      }
    },
    {
      "name": "Бас-гитара Rickenbacker 4001 Mapleglo USA 1974 w/ Case",
      "price": "921 990 ₽",
      "type": "used",
      "characteristics": {
        "codeOfItem": "553552",
        "type": "Бас-гитара",
        "nameOfBrand": "Rickenbacker",
        "series": "4000 Series",
        "condition": "Превосходное",
        "country": "США",
        "bodyShape": "Double cut",
        "orientation": "под правую руку",
        "valueOfStrings": "4",
        "valueOfFrets": "22",
        "widthOfUpperSill": "33.5",
        "deck": "клен",
        "neck": "клен",
        "fingerboard": "палисандр",
        "colorOfBody": "натуральный",
        "included": "кейс",
        "electronics": "пассивная",
        "pickupsSchema": "S-S",
        "fixingNeck": "на болтах",
        "article": "Вес: 5 кг"
      }
    },
    {
      "name": "Бас-гитара Fender Custom Edition Bass VI SSS Sunburst w/gigbag Japan 1992",
      "price": "878 990 ₽",
      "type": "used",
      "characteristics": {
        "codeOfItem": "524029",
        "type": "Бас-гитара",
        "nameOfBrand": "Fender",
        "condition": "Превосходное",
        "country": "Япония",
        "bodyShape": "Double cut",
        "orientation": "под правую руку",
        "valueOfStrings": "6",
        "valueOfFrets": "21",
        "widthOfUpperSill": "30",
        "widthOfUpperThreshold": "39.6",
        "deck": "ольха",
        "neck": "клен",
        "fingerboard": "палисандр",
        "colorOfBody": "санберст",
        "included": "чехол",
        "electronics": "пассивная",
        "pickupsSchema": "S-S-S",
        "fixingNeck": "на болтах",
        "article": "Вес: 5 кг"
      }
    },
    {
      "name": "Бас-гитара Hofner 500/1 Beatle Bass Vintage Violin Bass Germany 1974  w/Blade Pickups, Case",
      "price": "841 990 ₽",
      "type": "used",
      "characteristics": {
        "codeOfItem": "543172",
        "type": "Бас-гитара",
        "nameOfBrand": "Hofner",
        "series": "Beatle Bass",
        "condition": "Превосходное",
        "country": "Германия",
        "bodyShape": "Violin Bass",
        "orientation": "под правую руку",
        "valueOfStrings": "4",
        "valueOfFrets": "23",
        "widthOfUpperSill": "30",
        "deck": "клен",
        "neck": "клен",
        "fingerboard": "палисандр",
        "colorOfBody": "санберст",
        "included": "кейс",
        "electronics": "пассивная",
        "pickupsSchema": "S-S",
        "fixingNeck": "на клею",
        "article": "Вес: 5 кг"
      }
    },
    {
      "name": "Бас-гитара полуакустическая Hofner H500/1-61L Cavern Club '61 Violin Beatle Bass Left Handed w/case Germany",
      "price": "820 990 ₽",
      "type": "used",
      "characteristics": {
        "codeOfItem": "500335",
        "type": "Бас-гитара",
        "nameOfBrand": "Hofner",
        "condition": "Превосходное",
        "country": "Германия",
        "bodyShape": "Violin Bass",
        "orientation": "под левую руку",
        "valueOfStrings": "4",
        "valueOfFrets": "22",
        "widthOfUpperSill": "30",
        "widthOfUpperThreshold": "39.6",
        "deck": "клен, ель",
        "neck": "клен",
        "fingerboard": "палисандр",
        "colorOfBody": "санберст",
        "included": "кейс",
        "electronics": "пассивная",
        "pickupsSchema": "H-H",
        "fixingNeck": "на клею",
        "article": "Вес: 5 кг"
      }
    },
    {
      "name": "Бас-гитара Hofner 500/1 Beatle Bass Vintage Violin '60s 1978 Germany w/Case",
      "price": "781 990 ₽",
      "type": "used",
      "characteristics": {
        "codeOfItem": "518466",
        "type": "Бас-гитара",
        "nameOfBrand": "Hofner",
        "condition": "Превосходное",
        "country": "Германия",
        "bodyShape": "Violin Bass",
        "orientation": "под правую руку",
        "valueOfStrings": "4",
        "valueOfFrets": "22",
        "widthOfUpperSill": "30",
        "deck": "махагони",
        "neck": "клен",
        "fingerboard": "палисандр",
        "colorOfBody": "санберст",
        "included": "кейс",
        "electronics": "пассивная",
        "pickupsSchema": "H-H",
        "fixingNeck": "на клею",
        "article": "Вес: 5 кг"
      }
    },
    {
      "name": "Бас-гитара Hofner 500/1 Beatle Bass '60s Spec Vintage Violin Sunburst w/case Germany 1978",
      "price": "781 990 ₽",
      "type": "used",
      "characteristics": {
        "codeOfItem": "490126",
        "type": "Бас-гитара",
        "nameOfBrand": "Hofner",
        "condition": "Превосходное",
        "country": "Германия",
        "bodyShape": "Violin Bass",
        "orientation": "под правую руку",
        "valueOfStrings": "4",
        "valueOfFrets": "22",
        "widthOfUpperSill": "30",
        "widthOfUpperThreshold": "39.6",
        "deck": "клен, ель",
        "neck": "клен",
        "fingerboard": "палисандр",
        "colorOfBody": "санберст",
        "included": "кейс",
        "electronics": "пассивная",
        "pickupsSchema": "H-H",
        "fixingNeck": "на клею",
        "article": "175250065525",
        "weight": "5 кг"
      }
    },
    {
      "name": "Бас-гитара Gibson EB-0 Short Scale SG Bass Cherry w/case USA 1963",
      "price": "763 990 ₽",
      "type": "used",
      "characteristics": {
        "codeOfItem": "506095",
        "type": "Бас-гитара",
        "nameOfBrand": "Gibson",
        "condition": "Превосходное",
        "country": "США",
        "bodyShape": "SG",
        "orientation": "под правую руку",
        "valueOfStrings": "4",
        "valueOfFrets": "20",
        "widthOfUpperSill": "30.5",
        "widthOfUpperThreshold": "42.8",
        "deck": "махагони",
        "neck": "махагони",
        "fingerboard": "палисандр",
        "colorOfBody": "красный",
        "included": "кейс",
        "electronics": "пассивная",
        "pickupsSchema": "S",
        "fixingNeck": "на клею",
        "article": "Вес: 5 кг"
      }
    },
    {
      "name": "Бас-гитара Rickenbacker 4003S Vintage One-Owner Bass Guitar Fireglo USA 1988 w/Toaster Pickup, Case",
      "price": "746 990 ₽",
      "type": "used",
      "characteristics": {
        "codeOfItem": "544013",
        "type": "Бас-гитара",
        "nameOfBrand": "Rickenbacker",
        "series": "4000 Series",
        "condition": "Очень хорошее",
        "country": "США",
        "bodyShape": "Double cut",
        "orientation": "под правую руку",
        "valueOfStrings": "4",
        "valueOfFrets": "20",
        "widthOfUpperSill": "33.25",
        "widthOfUpperThreshold": "43",
        "deck": "клен",
        "neck": "клен",
        "fingerboard": "падук",
        "colorOfBody": "санберст",
        "included": "кейс",
        "electronics": "пассивная",
        "pickupsSchema": "H-S",
        "fixingNeck": "на клею",
        "article": "Вес: 5 кг"
      }
    },
    {
      "name": "Бас-гитара Gibson EB-0 Short Scale SG Bass Cherry USA 1962 w/Mudbucker",
      "price": "688 990 ₽",
      "type": "used",
      "characteristics": {
        "codeOfItem": "539922",
        "type": "Бас-гитара",
        "nameOfBrand": "Gibson",
        "condition": "Превосходное",
        "country": "США",
        "bodyShape": "SG",
        "orientation": "под правую руку",
        "valueOfStrings": "4",
        "valueOfFrets": "20",
        "widthOfUpperSill": "30.5",
        "deck": "махагони",
        "neck": "махагони",
        "fingerboard": "палисандр",
        "colorOfBody": "красный",
        "included": "кейс",
        "electronics": "пассивная",
        "pickupsSchema": "S",
        "fixingNeck": "на клею",
        "article": "Вес: 5 кг"
      }
    },
    {
      "name": "Бас-гитара Parker Fly Bass FB4 Quilted Maple USA 2003 w/Dimarzio Ultra Jazz & Piezo Pickups",
      "price": "686 990 ₽",
      "type": "used",
      "characteristics": {
        "codeOfItem": "532188",
        "type": "Бас-гитара",
        "nameOfBrand": "Parker",
        "condition": "Превосходное",
        "country": "США",
        "bodyShape": "Double cut",
        "orientation": "под правую руку",
        "valueOfStrings": "4",
        "valueOfFrets": "24",
        "widthOfUpperSill": "34",
        "deck": "ель",
        "neck": "карбон",
        "fingerboard": "черное дерево",
        "colorOfBody": "желтый",
        "included": "чехол",
        "electronics": "активная",
        "pickupsSchema": "H-H",
        "fixingNeck": "на клею",
        "article": "Вес: 5 кг"
      }
    },
    {
      "name": "Бас-гитара Hofner 500/1 Beatle Bass Vintage Violin w/case Germany 1979",
      "price": "668 990 ₽",
      "type": "used",
      "characteristics": {
        "codeOfItem": "490098",
        "type": "Бас-гитара",
        "nameOfBrand": "Hofner",
        "condition": "Превосходное",
        "country": "Германия",
        "bodyShape": "Violin Bass",
        "orientation": "под правую руку",
        "valueOfStrings": "4",
        "valueOfFrets": "22",
        "widthOfUpperSill": "30",
        "widthOfUpperThreshold": "38.1",
        "deck": "клен, ель",
        "neck": "клен",
        "fingerboard": "палисандр",
        "colorOfBody": "санберст",
        "included": "кейс",
        "electronics": "пассивная",
        "pickupsSchema": "H-H",
        "fixingNeck": "на клею",
        "article": "154945695475",
        "weight": "5 кг"
      }
    },
    {
      "name": "Бас-гитара Fender ExTrad 1962 Jazz Bass JB62-128 JJ Blonde w/case Japan 1989",
      "price": "631 990 ₽",
      "type": "used",
      "characteristics": {
        "codeOfItem": "551142",
        "type": "Бас-гитара",
        "nameOfBrand": "Fender",
        "condition": "Превосходное",
        "country": "Япония",
        "bodyShape": "Jazz Bass",
        "orientation": "под правую руку",
        "valueOfStrings": "4",
        "valueOfFrets": "20",
        "widthOfUpperSill": "34",
        "widthOfUpperThreshold": "38.1",
        "deck": "ясень",
        "neck": "клен",
        "fingerboard": "палисандр",
        "colorOfBody": "белый",
        "included": "кейс",
        "electronics": "пассивная",
        "pickupsSchema": "J-J",
        "fixingNeck": "на болтах",
        "article": "Вес: 5 кг"
      }
    },
    {
      "name": "Бас-гитара Fender American Vintage 1962 Jazz Bass JJ Olympic White w/case USA 2007",
      "price": "555 990 ₽",
      "type": "used",
      "characteristics": {
        "codeOfItem": "551144",
        "type": "Бас-гитара",
        "nameOfBrand": "Fender",
        "condition": "Превосходное",
        "country": "США",
        "bodyShape": "Jazz Bass",
        "orientation": "под правую руку",
        "valueOfStrings": "4",
        "valueOfFrets": "20",
        "widthOfUpperSill": "34",
        "widthOfUpperThreshold": "38.1",
        "deck": "ольха",
        "neck": "клен",
        "fingerboard": "палисандр",
        "colorOfBody": "белый",
        "included": "кейс",
        "electronics": "пассивная",
        "pickupsSchema": "J-J",
        "fixingNeck": "на болтах",
        "article": "Вес: 5 кг"
      }
    },
    {
      "name": "Бас-гитара Gibson RD Artist Bass Limited Run Antique Natural USA 2018 w/Case & Tags",
      "price": "538 990 ₽",
      "type": "used",
      "characteristics": {
        "codeOfItem": "553523",
        "type": "Бас-гитара",
        "nameOfBrand": "Gibson",
        "series": "RD Artist",
        "condition": "Превосходное",
        "country": "США",
        "bodyShape": "RD",
        "orientation": "под правую руку",
        "valueOfStrings": "4",
        "valueOfFrets": "20",
        "widthOfUpperSill": "34",
        "deck": "клен",
        "neck": "клен",
        "fingerboard": "палисандр",
        "colorOfBody": "натуральный",
        "included": "кейс",
        "electronics": "активная",
        "pickupsSchema": "H-H",
        "fixingNeck": "на клею",
        "article": "Вес: 5 кг"
      }
    },
    {
      "name": "Бас-гитара Mosrite Ventues Model Bass '64 Vintage Reissue Pearl White 2000 Japan",
      "price": "533 990 ₽",
      "type": "used",
      "characteristics": {
        "codeOfItem": "518464",
        "type": "Бас-гитара",
        "nameOfBrand": "Mosrite",
        "condition": "Очень хорошее",
        "country": "Япония",
        "bodyShape": "Double cut",
        "orientation": "под правую руку",
        "valueOfStrings": "4",
        "valueOfFrets": "20",
        "widthOfUpperSill": "30.5",
        "deck": "махагони",
        "neck": "клен",
        "fingerboard": "палисандр",
        "colorOfBody": "бежевый",
        "electronics": "пассивная",
        "pickupsSchema": "S",
        "fixingNeck": "на болтах",
        "article": "Вес: 5 кг"
      }
    },
    {
      "name": "Бас-гитара Kramer DMZ 5000 Aluminum PJ DiMarzio White w/gigbag USA 1981",
      "price": "515 990 ₽",
      "type": "used",
      "characteristics": {
        "codeOfItem": "500544",
        "type": "Бас-гитара",
        "nameOfBrand": "Kramer",
        "condition": "Превосходное",
        "country": "США",
        "bodyShape": "Double cut",
        "orientation": "под правую руку",
        "valueOfStrings": "4",
        "valueOfFrets": "20",
        "widthOfUpperSill": "33.75",
        "widthOfUpperThreshold": "41.2",
        "deck": "клен",
        "neck": "алюминий",
        "fingerboard": "эбонол",
        "colorOfBody": "белый",
        "included": "чехол",
        "electronics": "пассивная",
        "pickupsSchema": "P-J",
        "fixingNeck": "на болтах",
        "article": "Вес: 5 кг"
      }
    },
    {
      "name": "Бас-гитара Fender Jino Jazz Bass SHS Seafoam Green Japan 2020 w/Active EQ & Tweed Case",
      "price": "498 990 ₽",
      "type": "used",
      "characteristics": {
        "codeOfItem": "552519",
        "type": "Бас-гитара",
        "nameOfBrand": "Fender",
        "condition": "Превосходное",
        "country": "Япония",
        "bodyShape": "Jazz Bass",
        "orientation": "под правую руку",
        "valueOfStrings": "4",
        "valueOfFrets": "20",
        "widthOfUpperSill": "34",
        "deck": "ясень",
        "neck": "клен",
        "fingerboard": "палисандр",
        "colorOfBody": "голубой",
        "included": "кейс",
        "electronics": "активная",
        "pickupsSchema": "H, J-J",
        "fixingNeck": "на болтах",
        "article": "Вес: 5 кг"
      }
    },
    {
      "name": "Бас-гитара 1997 Gibson Les Paul Standard Bass Vintage Sunburst w/Case, Active Bartolini Preamp",
      "price": "481 990 ₽",
      "type": "used",
      "characteristics": {
        "codeOfItem": "544053",
        "type": "Бас-гитара",
        "nameOfBrand": "Gibson",
        "series": "Les Paul Standard",
        "condition": "Превосходное",
        "country": "США",
        "bodyShape": "Les Paul",
        "orientation": "под правую руку",
        "valueOfStrings": "4",
        "valueOfFrets": "20",
        "widthOfUpperSill": "34",
        "deck": "махагони",
        "neck": "махагони",
        "fingerboard": "черное дерево",
        "colorOfBody": "санберст",
        "included": "кейс",
        "electronics": "активная",
        "pickupsSchema": "H-H",
        "fixingNeck": "на клею",
        "article": "Вес: 5 кг"
      }
    },
    {
      "name": "Бас-гитара B.C. Rich NJ Series Warlock Black Nikki Sixx Japan 1986",
      "price": "478 990 ₽",
      "type": "used",
      "characteristics": {
        "codeOfItem": "551432",
        "type": "Бас-гитара",
        "nameOfBrand": "B.C.Rich",
        "series": "NJ Series",
        "condition": "Превосходное",
        "country": "Япония",
        "bodyShape": "Warlock",
        "orientation": "под правую руку",
        "valueOfStrings": "4",
        "valueOfFrets": "24",
        "widthOfUpperSill": "34",
        "deck": "ольха",
        "neck": "клен",
        "fingerboard": "палисандр",
        "colorOfBody": "черный",
        "included": "чехол",
        "electronics": "активная",
        "pickupsSchema": "P-P",
        "fixingNeck": "на болтах",
        "article": "Вес: 5 кг"
      }
    },
    {
      "name": "Бас-гитара Mosrite Custom 1965 Ventures Model Bass SS Pearl White w/gigbag Japan 2000s",
      "price": "477 990 ₽",
      "type": "used",
      "characteristics": {
        "codeOfItem": "530862",
        "type": "Бас-гитара",
        "nameOfBrand": "Mosrite",
        "condition": "Превосходное",
        "country": "Япония",
        "bodyShape": "Double cut",
        "orientation": "под правую руку",
        "valueOfStrings": "4",
        "valueOfFrets": "20",
        "widthOfUpperSill": "30.5",
        "widthOfUpperThreshold": "39.6",
        "deck": "липа",
        "neck": "клен",
        "fingerboard": "палисандр",
        "colorOfBody": "белый",
        "included": "чехол",
        "electronics": "пассивная",
        "pickupsSchema": "S-S",
        "fixingNeck": "на болтах",
        "article": "Вес: 5 кг"
      }
    }
  ]
}
